{
    "description": "Provided to YouTube by The Orchard EnterprisesGuerra y destruccion · RipHistoria viva del punk\\xe2\\x84\\x97 2005 Gaztelupeko HotsakReleased on: 2006-08-08Auto-generated ...",
    "duration": "1:21",
    "image": "https://i.ytimg.com/vi/6Bd-5Y23iDc/maxresdefault.jpg",
    "keywords": "Rip, Historia, viva, del, punk, Guerra, destruccion",
    "title": "Guerra y destruccion",
    "url": "https://github.com/circuitalmynds/music_i2/blob/main/videos/Guerra y destruccion-6Bd-5Y23iDc.mp4?raw=true"
}