{
    "description": "From Timecop1983 - Night Drive. Get it at: https://timecop1983.bandcamp.com/album/night-drive or on all major streaming platforms.Comments are turned off. Th...",
    "duration": "5:01",
    "image": "https://i.ytimg.com/vi/_Ci0Kgdpgsw/maxresdefault.jpg",
    "keywords": "80s, 80's, eighties, synthpop, synthwave, dreamwave, retrowave, newretrowave, nrw, timecop1983, cyberpunk, cinematic, soundtrack, ambient",
    "title": "Timecop1983 - On the Run",
    "url": "https://github.com/circuitalmynds/music_w1/blob/main/videos/Timecop1983 - On the Run-_Ci0Kgdpgsw.mp4?raw=true"
}