{
    "description": "HOY NO QUIERO CANTARLeonardo FavioCierro los ojos, lo pienso, hoy no quiero cantartantos faltan a mi lado, tantos que me quisieron.Mi abuelita, si me parece ...",
    "duration": "3:49",
    "image": "https://i.ytimg.com/vi/_WVQ5XhD5MA/maxresdefault.jpg",
    "keywords": "Leonardo Favio, Hoy no quiero cantar, canción, triste, melancolía, soledad",
    "title": "Leonardo Favio HOY NO QUIERO CANTAR",
    "url": "https://github.com/circuitalmynds/music_k1/blob/main/videos/Leonardo Favio HOY NO QUIERO CANTAR-_WVQ5XhD5MA.mp4?raw=true"
}