{
    "description": "Discuss/review/recommend the work at https://classicalmusiconly.com/work/camille-saint-saens/the-carnival-of-the-animals-ca8cTitle : Saint-Saens : The SwanFr...",
    "duration": "3:28",
    "image": "https://i.ytimg.com/vi/b44-5M4e9nI/hqdefault.jpg",
    "keywords": "Saint, Saens, Saëns, The, Swan, Le, Cygne, Carnival, of, the, Animals, classical, world, music",
    "title": "Saint-Saens : The Swan ( Le Cygne )  - Carnival of the Animals",
    "url": "https://github.com/circuitalmynds/music_t2/blob/main/videos/Saint-Saens  - The Swan ( Le Cygne )  - Carnival of the Animals-b44-5M4e9nI.mp4?raw=true"
}