{
    "description": "Provided to YouTube by Universal Music GroupThe Dream · The CureJoin The Dots - The B-Sides & Rarities\\xe2\\x84\\x97 1983 Fiction Records Ltd.Released on: 2004-01-01Assoc...",
    "duration": "3:12",
    "image": "https://i.ytimg.com/vi/B7pq2sYjQq0/maxresdefault.jpg",
    "keywords": "The Cure, \\xe3\\x82\\xb6\\xe3\\x82\\xad\\xe3\\x83\\xa5\\xe3\\x82\\xa2\\xe3\\x83\\xbc, \\xe3\\x82\\xb6\\xe3\\x83\\xbb\\xe3\\x82\\xad\\xe3\\x83\\xa5\\xe3\\x82\\xa2\\xe3\\x83\\xbc, Join The Dots - The B-Sides & Rarities, The Dream",
    "title": "The Dream",
    "url": "https://github.com/circuitalmynds/music_t1/blob/main/videos/The Dream-B7pq2sYjQq0.mp4?raw=true"
}