{
    "description": "Mama, Don't Cry At My Wedding ~ Sue Thompson (1964) Hickory # 45-1284 -The flip side of,  Paper Tiger (* Words & Music by: Helen Hudgins)",
    "duration": "2:14",
    "image": "https://i.ytimg.com/vi/cL5VW5g0I6k/hqdefault.jpg",
    "keywords": "Sue Thompson, Mama Don't Cry At My Wedding, Paper Tiger",
    "title": "Mama, Don't Cry At My Wedding ~ Sue Thompson (1964)",
    "url": "https://github.com/circuitalmynds/music_c/blob/main/videos/Mama, Don't Cry At My Wedding ~ Sue Thompson (1964)-cL5VW5g0I6k.mp4?raw=true"
}