{
    "description": "Provided to YouTube by The Orchard EnterprisesLa Huella Mia · Chuy VegaCon un Nudo en la Garganta\\xe2\\x84\\x97 2004 Hyphy MusicReleased on: 2004-03-12Auto-generated by Y...",
    "duration": "3:12",
    "image": "https://i.ytimg.com/vi/dfGgv430E04/maxresdefault.jpg",
    "keywords": "Chuy, Vega, Con, un, Nudo, en, la, Garganta, La, Huella, Mia",
    "title": "La Huella Mia",
    "url": "https://github.com/circuitalmynds/music_g2/blob/main/videos/La Huella Mia-dfGgv430E04.mp4?raw=true"
}