{
    "description": "Best of OMD: https://goo.gl/dhrWz8Subscribe here: https://goo.gl/aYdtmEMusic video by Orchestral Manoeuvres In The Dark performing Secret. (P) 1985 The copyr...",
    "duration": "3:51",
    "image": "https://i.ytimg.com/vi/EtYre1GABao/maxresdefault.jpg",
    "keywords": "Orchestral, Manoeuvres, In, The, Dark, Secret, Virgin, Catalogue, Electronic/Dance",
    "title": "Orchestral Manoeuvres In The Dark - Secret",
    "url": "https://github.com/circuitalmynds/music_f1/blob/main/videos/Orchestral Manoeuvres In The Dark - Secret-EtYre1GABao.mp4?raw=true"
}