{
    "description": "The original video is by atg_filmlover, I have only improved the video quality from 644x480 to 1920x1080",
    "duration": "4:15",
    "image": "https://i.ytimg.com/vi/HLBDFXX23ao/maxresdefault.jpg",
    "keywords": "Mariya Takeuchi, Mariya, Takeuchi, Music, Musica, City-pop, CityPop, City pop, City Pop, Singer, Famous Singer, Live, Mariya Takeuchi 竹内まりや - September (LIVE 1980), Mariya Takeuchi - September, September, September song, Chill, Relax, Japan, Japanese, Music live, Ultra HD, 1980, 1980 Japan, Japanese girl, 竹内まりや, Subtitle, Japanese subtitle, Romaji, Japanese romanization, English subtitle, Credit",
    "title": "Mariya Takeuchi 竹内まりや    September LIVE 1980 Ultra HD version",
    "url": "https://github.com/circuitalmynds/music_l2/blob/main/videos/Mariya Takeuchi 竹内まりや    September LIVE 1980 Ultra HD version-HLBDFXX23ao.mp4?raw=true"
}