{
    "description": "\"Rock-A-Beatin' Boogie\" is a 1952 song composed by Bill Haley and first recorded by The Esquire Boys in 1952. It was recorded by Bill Haley and the Comets on...",
    "duration": "2:17",
    "image": "https://i.ytimg.com/vi/Iql9016msD0/hqdefault.jpg",
    "keywords": "rock, beatin, boogie, bill, haley",
    "title": "Rock-A-Beatin' Boogie [Bill Haley]",
    "url": "https://github.com/circuitalmynds/music_r/blob/main/videos/Rock-A-Beatin' Boogie [Bill Haley]-Iql9016msD0.mp4?raw=true"
}