{
    "description": "Provided to YouTube by RCA Records LabelTraficando Rimas · Cartel de Santa · Bicho RamirezSincopa\\xe2\\x84\\x97 2010 Sony Music Entertainment México, S.A. De C.V.Released...",
    "duration": "4:36",
    "image": "https://i.ytimg.com/vi/jgRaGy9b35o/maxresdefault.jpg",
    "keywords": "Cartel de Santa, \\xe8\\x81\\x96\\xe5\\xbe\\x92\\xe5\\x8d\\xa1\\xe7\\x89\\xb9\\xe7\\x88\\xbe, Bicho Ramirez, Sincopa, Traficando Rimas",
    "title": "Traficando Rimas",
    "url": "https://github.com/circuitalmynds/music_t/blob/main/videos/Traficando Rimas-jgRaGy9b35o.mp4?raw=true"
}