{
    "description": "Provided to YouTube by Universal Music GroupLondon Dungeon · MisfitsCollection\\xe2\\x84\\x97 1981 Caroline Records IncReleased on: 1986-01-01Associated  Performer, Vocals...",
    "duration": "2:35",
    "image": "https://i.ytimg.com/vi/JrvHzIJ6zx8/maxresdefault.jpg",
    "keywords": "Misfits, \\xe3\\x83\\x9f\\xe3\\x82\\xb9\\xe3\\x83\\x95\\xe3\\x82\\xa3\\xe3\\x83\\x83\\xe3\\x83\\x84, Collection, London Dungeon",
    "title": "London Dungeon",
    "url": "https://github.com/circuitalmynds/music_q/blob/main/videos/London Dungeon-JrvHzIJ6zx8.mp4?raw=true"
}