{
    "description": "Artist:  Travis Barker feat. Paul Wall, Jay Rock & KuruptSong:  Don't Fuck With MeAlbum:  Give The Drummer SomeArtwork:  Dire Onehttp://itunes.apple.com/us/a...",
    "duration": "4:23",
    "image": "https://i.ytimg.com/vi/KzgMs_jZOJQ/hqdefault.jpg",
    "keywords": "Travis, Barker, Paul, Wall, Jay, Rock, Kurupt, Don't, Fuck, With, Me, Dire, One, Give, The, Drummer, Some",
    "title": "Travis Barker feat. Paul Wall, Jay Rock & Kurupt - Don't Fuck With Me",
    "url": "https://github.com/circuitalmynds/music_t/blob/main/videos/Travis Barker feat. Paul Wall, Jay Rock & Kurupt - Don't Fuck With Me-KzgMs_jZOJQ.mp4?raw=true"
}