{
    "description": "Provided to YouTube by Universal Music GroupLa Muerte Del Torito (En Vivo) · Chalino SanchezChalino Sánchez Y Sus Compas\\xe2\\x84\\x97 2001 Musart-Balboa, a division of C...",
    "duration": "5:08",
    "image": "https://i.ytimg.com/vi/LbPph6Hmai4/maxresdefault.jpg",
    "keywords": "Chalino Sanchez, Chalino Sánchez Y Sus Compas, La Muerte Del Torito",
    "title": "La Muerte Del Torito (En Vivo)",
    "url": "https://github.com/circuitalmynds/music_x1/blob/main/videos/La Muerte Del Torito (En Vivo)-LbPph6Hmai4.mp4?raw=true"
}