{
    "description": "Facebook: https://www.facebook.com/pierocantautorTwitter: https://twitter.com/PieroCantautorContrataciones: informacion@pieroonline.com\"MI VIEJO\" - 1969 Estu...",
    "duration": "2:59",
    "image": "https://i.ytimg.com/vi/lEnAo9tCbfs/hqdefault.jpg",
    "keywords": "musica 2013, musica de piero, BeToYou, rock, piero, musica rock, de vez en cuando, BeToYou Network",
    "title": "Piero - De Vez En Cuando Viene Bien Dormir [Canción Oficial] ®",
    "url": "https://github.com/circuitalmynds/music_c/blob/main/videos/Piero - De Vez En Cuando Viene Bien Dormir [Canción Oficial] ®-lEnAo9tCbfs.mp4?raw=true"
}