{
    "description": "Provided to YouTube by Universal Music GroupF.D.R. Jones · Ella Fitzgerald · Chick Webb And His OrchestraThe Early Years - Part 1 (1935-1938)℗ 1938 Verve Lab...",
    "duration": "2:53",
    "image": "https://i.ytimg.com/vi/lnSPDJgwgcU/maxresdefault.jpg",
    "keywords": "Ella Fitzgerald, エラフィッツジェラルド, エラ・フィッツジェラルド, Chick Webb And His Orchestra, ＣｈｉｃｋＷｅｂｂＡｎｄＨｉｓＯｒｃｈｅｓｔｒａ, The Early Years - Part 1 (1935-1938), F.D.R. Jones",
    "title": "F.D.R. Jones",
    "url": "https://github.com/circuitalmynds/music_n1/blob/main/videos/F.D.R. Jones-lnSPDJgwgcU.mp4?raw=true"
}