{
    "description": "Lupe Tijerina & Genaro Cruz",
    "duration": "3:43",
    "image": "https://i.ytimg.com/vi/niOx1LrvsQY/hqdefault.jpg",
    "keywords": "Los cadetes de linares, Don anselmo y el cuervo, busca otro amor, el botas blancas, lupe tijerina, genaro cruz, homero guerrero, linares, nuevo leon",
    "title": "Los Cadetes De Linares - Don Anselmo y el Cuervo (Lupe Tijerina & Genaro Cruz)",
    "url": "https://github.com/circuitalmynds/music_v1/blob/main/videos/Los Cadetes De Linares - Don Anselmo y el Cuervo (Lupe Tijerina & Genaro Cruz)-niOx1LrvsQY.mp4?raw=true"
}