{
    "description": "This song pays tribute to David Bowie's \"Space Oddity\" by name checking Major Tom but Peter Schilling admits he used the name but took his inspiration for th...",
    "duration": "9:09",
    "image": "https://i.ytimg.com/vi/rRD-d-_EzIc/hqdefault.jpg",
    "keywords": "video, compartir, teléfono con cámara, teléfono con video, gratuito, subir",
    "title": "Peter Schilling ~ Major Tom (Coming Home) 1983 New Wave XTension",
    "url": "https://github.com/circuitalmynds/music_p/blob/main/videos/Peter Schilling ~ Major Tom (Coming Home) 1983 New Wave XTension-rRD-d-_EzIc.mp4?raw=true"
}