{
    "description": "Provided to YouTube by The Orchard EnterprisesPreso Por Vida · Los Gatos De SinaloaPerro De Cadena\\xe2\\x84\\x97 2011 EgoReleased on: 2011-05-13Auto-generated by YouTube.",
    "duration": "2:37",
    "image": "https://i.ytimg.com/vi/S_OvN8w3Eo0/maxresdefault.jpg",
    "keywords": "Los, Gatos, De, Sinaloa, Perro, Cadena, Preso, Por, Vida",
    "title": "Preso Por Vida",
    "url": "https://github.com/circuitalmynds/music_p/blob/main/videos/Preso Por Vida-S_OvN8w3Eo0.mp4?raw=true"
}