{
    "description": "The official music video for \"Gangsters and Thugs\" by Transplants from the album 'Haunted Cities'.Subscribe for more official content from Atlantic Records:h...",
    "duration": "3:33",
    "image": "https://i.ytimg.com/vi/UfNBpNWWhak/maxresdefault.jpg",
    "keywords": "Warner Music, Atlantic Records, Transplants - Gangsters and Thugs (Official Audio), Transplants - Gangsters and Thugs, Gangsters and Thugs (Official Audio), Official Audio, transplants gangsters and thugs, transplants gangsters & thugs, gangsers and thugs transplants, gangsters & thugs - transplants, gangsters and thugs official audio, the transplants, the transplants gangsters and thugs, gangsters and thugs transplants, gangsters and thugs, music video, transplants music video",
    "title": "Transplants - Gangsters and Thugs (Music Video)",
    "url": "https://github.com/circuitalmynds/music_w1/blob/main/videos/Transplants - Gangsters and Thugs (Music Video)-UfNBpNWWhak.mp4?raw=true"
}