{
    "description": "Best of OMD: https://goo.gl/dhrWz8Subscribe here: https://goo.gl/aYdtmEMusic video by Orchestral Manoeuvres In The Dark performing Talking Loud And Clear. (P...",
    "duration": "3:56",
    "image": "https://i.ytimg.com/vi/Ujg7xHZ-nrE/maxresdefault.jpg",
    "keywords": "Orchestral, Manoeuvres, In, The, Dark, Talking, Loud, And, Clear, Virgin, Catalogue, Electronic/Dance",
    "title": "Orchestral Manoeuvres In The Dark - Talking Loud And Clear",
    "url": "https://github.com/circuitalmynds/music_c2/blob/main/videos/Orchestral Manoeuvres In The Dark - Talking Loud And Clear-Ujg7xHZ-nrE.mp4?raw=true"
}