{
    "description": "Vídeo oficial de José José de su tema Mi Vada. Haz clic aquí para escuchar a José José en Spotify: http://smarturl.it/JJSpot?IQid=JJMVIncluido en Mi Vida. Ha...",
    "duration": "4:11",
    "image": "https://i.ytimg.com/vi/UTKhKGOne5w/maxresdefault.jpg",
    "keywords": "Desesperado, Almohada, José José en vivo, vídeo, Mi Vada en vivo, José José Oficial, José José letra, Lo Que No Fue No Sera, en vivo, Si Me Dejas Ahora, Soy Asi, instrumental, álbum, José José Mi Vada, música, hd, Me Vas A Echar De Menos, vevo, Payaso, JoseJoseVEVO, oficial, José José, El Amor Acaba, karaoke, remix, portada, audio, El Triste, Gavilan o Paloma, El, Sony, Vamos A Darnos Tiempo, acústico, video oficial, Mi Vada letra, descarga",
    "title": "José José - Mi Vida (Cover Audio)",
    "url": "https://github.com/circuitalmynds/music_j/blob/main/videos/José José - Mi Vida (Cover Audio)-UTKhKGOne5w.mp4?raw=true"
}