{
    "description": "Elvis\\xe2\\x80\\x99 first album was rapidly assembled to capitalize on the gathering success of the single. The album included three tracks from the Nashville session, fo...",
    "duration": "2:33",
    "image": "https://i.ytimg.com/vi/vbcMH7KCKCA/hqdefault.jpg",
    "keywords": "Elvis Presley, Just Because, 1956",
    "title": "Elvis Presley - Just Because (1956)",
    "url": "https://github.com/circuitalmynds/music_k/blob/main/videos/Elvis Presley - Just Because (1956)-vbcMH7KCKCA.mp4?raw=true"
}