{
    "description": "",
    "duration": "7:19",
    "image": "https://i.ytimg.com/vi/wNQqAeYeWIQ/maxresdefault.jpg",
    "keywords": "Megamix, Front, 242, Jarre, Kraftwerk, Enya, Delerium, Art, Of, Noise, Ivan, Erasure, Mo, Do, Eins, Zwei, Mix, L",
    "title": "Megamix Front 242 Jarre Kraftwerk Enya Delerium Art Of Noise Ivan Erasure Mo Do   Eins Zwei Mix L",
    "url": "https://github.com/circuitalmynds/music_x/blob/main/videos/Megamix Front 242 Jarre Kraftwerk Enya Delerium Art Of Noise Ivan Erasure Mo Do   Eins Zwei Mix L-wNQqAeYeWIQ.mp4?raw=true"
}