{
    "description": "From \"Nothing Is Sound\" available now!Buy it on iTunes: smarturl.it/NothingIsSoundStream it on Spotify: smarturl.it/S_NothingIsSound© 2005 Sparrow/Columbia R...",
    "duration": "4:19",
    "image": "https://i.ytimg.com/vi/zzFvyr77XGw/maxresdefault.jpg",
    "keywords": "Switchfoot (Musical Group), Daisy (Canonical Version), Music (TV Genre)",
    "title": "Switchfoot - Daisy [Official Audio]",
    "url": "https://github.com/circuitalmynds/music_s/blob/main/videos/Switchfoot - Daisy [Official Audio]-zzFvyr77XGw.mp4?raw=true"
}